{
  "key": "basket-view-page",
  "name": "Basket view page",
  "type": "ui-feature",
  "elementType": "ui-page",
  "uri": "/Basket",
  "location": "src/Web/Pages/Basket/Index.cshtml",
  "codeBehind": "src/Web/Pages/Basket/Index.cshtml.cs",
  "domain": "basket",
  "notes": [
    "Handles three operations on one page: view (OnGet), add-item (OnPost), update-quantities (OnPostUpdate).",
    "Anonymous users are tracked by a GUID stored in a cookie; authenticated users use their username.",
    "POST from catalog's [ADD TO BASKET] lands here as OnPost with CatalogItemViewModel."
  ]
}
